huaweicloudsdkaad/__init__.py
huaweicloudsdkaad/v1/__init__.py
huaweicloudsdkaad/v1/aad_async_client.py
huaweicloudsdkaad/v1/aad_client.py
huaweicloudsdkaad/v1/model/__init__.py
huaweicloudsdkaad/v1/model/add_black_white_ip_list_request.py
huaweicloudsdkaad/v1/model/add_black_white_ip_list_response.py
huaweicloudsdkaad/v1/model/add_policy_black_and_white_ip_list_request.py
huaweicloudsdkaad/v1/model/add_policy_black_and_white_ip_list_response.py
huaweicloudsdkaad/v1/model/alarm_body.py
huaweicloudsdkaad/v1/model/associate_ip_to_policy_and_package_request.py
huaweicloudsdkaad/v1/model/associate_ip_to_policy_and_package_response.py
huaweicloudsdkaad/v1/model/associate_ip_to_policy_request.py
huaweicloudsdkaad/v1/model/associate_ip_to_policy_response.py
huaweicloudsdkaad/v1/model/batch_create_instance_ip_rule_request.py
huaweicloudsdkaad/v1/model/batch_create_instance_ip_rule_response.py
huaweicloudsdkaad/v1/model/batch_delete_instance_ip_rule_request.py
huaweicloudsdkaad/v1/model/batch_delete_instance_ip_rule_response.py
huaweicloudsdkaad/v1/model/batch_id_body.py
huaweicloudsdkaad/v1/model/batch_transfer_rule_body.py
huaweicloudsdkaad/v1/model/black_white_ip_list_request.py
huaweicloudsdkaad/v1/model/black_white_ip_request_body.py
huaweicloudsdkaad/v1/model/block_list_blocking_list.py
huaweicloudsdkaad/v1/model/bw.py
huaweicloudsdkaad/v1/model/cad_domain_switch_request.py
huaweicloudsdkaad/v1/model/certificate_body.py
huaweicloudsdkaad/v1/model/create_domain_request.py
huaweicloudsdkaad/v1/model/create_domain_response.py
huaweicloudsdkaad/v1/model/create_policy_request.py
huaweicloudsdkaad/v1/model/create_policy_request_body.py
huaweicloudsdkaad/v1/model/create_policy_response.py
huaweicloudsdkaad/v1/model/delete_alarm_config_request.py
huaweicloudsdkaad/v1/model/delete_alarm_config_response.py
huaweicloudsdkaad/v1/model/delete_black_white_ip_list_request.py
huaweicloudsdkaad/v1/model/delete_black_white_ip_list_response.py
huaweicloudsdkaad-3.1.184.dist-info/METADATA
huaweicloudsdkaad-3.1.184.dist-info/WHEEL
huaweicloudsdkaad-3.1.184.dist-info/licenses/LICENSE
huaweicloudsdkaad-3.1.184.dist-info/RECORD
